{
    "$schema": "http://json-schema.org/draft-07/schema#",
    "title": "CVModel",
    "type": "object",
    "properties": {
        "id": {
            "type": "integer"
        },
        "freelancer_id": {
            "type": "integer"
        },
        "employee_id": {
            "type": "integer"
        },
        "applicant_id": {
            "type": "integer"
        },
        "name": {
            "type": "string"
        },
        "cv_raw_text": {
            "type": "string"
        },
        "cv_structured_data": {
            "type": "string"
        },
        "cv_schema_reference": {
            "type": "integer"
        },
        "created_at": {
            "type": "string",
            "default": "<function datetime.utcnow at 0x000001D8FFB42CA0>"
        },
        "updated_at": {
            "type": "string",
            "default": "<function datetime.utcnow at 0x000001D8FFB42D40>"
        }
    },
    "required": [
        "id",
        "name",
        "cv_raw_text",
        "cv_structured_data",
        "cv_schema_reference"
    ]
}